penaltymodel/__init__.py
penaltymodel/cache.py
penaltymodel/database.py
penaltymodel/exceptions.py
penaltymodel/generation.py
penaltymodel/interface.py
penaltymodel/lp.py
penaltymodel/maxgap.py
penaltymodel/mip.py
penaltymodel/typing.py
penaltymodel/utils.py
penaltymodel/core/__init__.py
penaltymodel/core/exceptions.py
penaltymodel/core/interface.py
penaltymodel/core/package_info.py
penaltymodel/core/classes/__init__.py
penaltymodel/core/classes/penaltymodel.py
penaltymodel/core/classes/specification.py
penaltymodel-1.1.0.dist-info/LICENSE
penaltymodel-1.1.0.dist-info/METADATA
penaltymodel-1.1.0.dist-info/WHEEL
penaltymodel-1.1.0.dist-info/top_level.txt
penaltymodel-1.1.0.dist-info/RECORD
