Metadata-Version: 2.1
Name: penaltymodel
Version: 1.1.0
Summary: Package for creating penalty models.
Home-page: https://github.com/dwavesystems/penaltymodel
Author: D-Wave Systems Inc.
Author-email: tools@dwavesys.com
License: Apache 2.0
Project-URL: Changes, https://github.com/dwavesystems/penaltymodel/releases
Project-URL: Documentation, https://docs.ocean.dwavesys.com
Project-URL: Souce Code, https://github.com/dwavesystems/penaltymodel
Classifier: License :: OSI Approved :: Apache Software License
Classifier: Operating System :: OS Independent
Classifier: Programming Language :: Python :: 3 :: Only
Classifier: Programming Language :: Python :: 3.8
Classifier: Programming Language :: Python :: 3.9
Classifier: Programming Language :: Python :: 3.10
Classifier: Programming Language :: Python :: 3.11
Classifier: Programming Language :: Python :: 3.12
Requires-Python: >=3.8
License-File: LICENSE
Requires-Dist: dimod>=0.10.9
Requires-Dist: homebase>=1.0.1
Requires-Dist: networkx>=2.4.0
Requires-Dist: numpy>=1.20.0
Requires-Dist: scipy>=1.6.0
